pymuco/AudioConverter.py
pymuco/Chord.py
pymuco/CircleOfFifths.py
pymuco/Enharmonic.py
pymuco/EnharmonicMapping.py
pymuco/Interval.py
pymuco/KeySignature.py
pymuco/MIDIUtils.py
pymuco/MidiGenerator.py
pymuco/MusicComputationNotation.py
pymuco/MusicData.py
pymuco/NoteDuration.py
pymuco/NoteFrequencyConverter.py
pymuco/NoteMapping.py
pymuco/Player.py
pymuco/Scale.py
pymuco/ScientificPitchNotation.py
pymuco/Tonality.py
pymuco/__init__ .py
pymuco/__init__.py
pymuco/logging_utils.py
pymuco/test/__init__.py
pymuco/test/test_audio_converter.py
pymuco/test/test_chord.py
pymuco/test/test_circle_of_fifths.py
pymuco/test/test_enharmonic.py
pymuco/test/test_enharmonic_mapping.py
pymuco/test/test_interval.py
pymuco/test/test_key_signature.py
pymuco/test/test_midi_generator.py
pymuco/test/test_midi_utils.py
pymuco/test/test_music_computation_notation.py
pymuco/test/test_note_duration.py
pymuco/test/test_note_frequency_converter.py
pymuco/test/test_note_mapping.py
pymuco/test/test_player.py
pymuco/test/test_scale.py
pymuco/test/test_scientific_pitch_notation.py
pymuco/test/test_tonality.py
pymuco-1.1.6.dist-info/LICENSE
pymuco-1.1.6.dist-info/METADATA
pymuco-1.1.6.dist-info/WHEEL
pymuco-1.1.6.dist-info/top_level.txt
pymuco-1.1.6.dist-info/RECORD
